{"cell": "gemma-4-26b-a4b-it-nitro__hle", "question_id": "66ec6ad7b64b08f801db4fde", "benchmark": "hle", "domain": "M", "question": "How many positive definite even lattices are there of dimension 17 and determinant 2?", "segments": [{"seg_id": 0, "text": "The question asks for the number of positive definite even lattices of dimension $n = 17$ and determinant $d = 2$."}, {"seg_id": 1, "text": "*   $n = 17$ (dimension)"}, {"seg_id": 2, "text": "*   $d = 2$ (determinant)"}, {"seg_id": 3, "text": "*   $L$ is a positive definite even lattice."}, {"seg_id": 4, "text": "*   $L$ is even $\\implies Q(x) = \\frac{1}{2}x^T A x \\in \\mathbb{Z}$ for all $x \\in L$, where $A$ is the Gram matrix."}, {"seg_id": 5, "text": "The diagonal entries of $A$ are even."}, {"seg_id": 6, "text": "*   The determinant of the Gram matrix $A$ is $d = 2$."}, {"seg_id": 7, "text": "*   A lattice $L$ is unimodular if $d = 1$."}, {"seg_id": 8, "text": "*   If $L$ is an even lattice, then $n$ must be a multiple of 8 for $d=1$."}, {"seg_id": 9, "text": "Since $n=17$, there are no even unimodular lattices."}, {"seg_id": 10, "text": "*   Wait, the question is about even lattices of determinant 2."}, {"seg_id": 11, "text": "*   An even lattice $L$ of dimension $n$ and determinant $d$ corresponds to a quadratic form."}, {"seg_id": 12, "text": "*   The classification of even lattices often involves looking at the genus."}, {"seg_id": 13, "text": "*   The discriminant group $L^*/L$ is a finite abelian group of order $d = \\det(L)$."}, {"seg_id": 14, "text": "*   In our case, $d = 2$, so the discriminant group is $\\mathbb{Z}/2\\mathbb{Z}$."}, {"seg_id": 15, "text": "*   The discriminant form $q: L^*/L \\to \\mathbb{Q}/2\\mathbb{Z}$ (or $\\mathbb{Q}/\\mathbb{Z}$ depending on normalization) is defined by $q(x + L) = x^2 \\pmod{2\\mathbb{Z}}$."}, {"seg_id": 16, "text": "*   For $d=2$, $L^*/L \\cong \\mathbb{Z}/2\\mathbb{Z}$."}, {"seg_id": 17, "text": "Let $v$ be the non-zero element in $L^*/L$."}, {"seg_id": 18, "text": "*   The value $q(v)$ must be $1/2 \\pmod{1}$ or something similar?"}, {"seg_id": 19, "text": "Let's be careful."}, {"seg_id": 20, "text": "*   For an even lattice, the quadratic form on the discriminant group $A_L = L^*/L$ is $q(x+L) = x \\cdot x \\pmod{2\\mathbb{Z}}$."}, {"seg_id": 21, "text": "*   If $L$ is even, $x \\cdot x \\in 2\\mathbb{Z}$ for $x \\in L$."}, {"seg_id": 22, "text": "For $x \\in L^*$, $x \\cdot x \\in \\mathbb{Q}$."}, {"seg_id": 23, "text": "*   The discriminant form $q$ is a map $A_L \\to \\mathbb{Q}/2\\mathbb{Z}$."}, {"seg_id": 24, "text": "*   Since $|A_L| = 2$, the non-zero element $v$ must satisfy $2v = 0$."}, {"seg_id": 25, "text": "*   The possible values for $q(v)$ in $\\mathbb{Q}/2\\mathbb{Z}$ are $1/2$ and $1$."}, {"seg_id": 26, "text": "Wait, $q(v)$ must be such that $2q(v) \\in 2\\mathbb{Z}$?"}, {"seg_id": 27, "text": "No, $q(v+v) = q(2v) = 4q(v) \\equiv 0 \\pmod{2\\mathbb{Z}}$."}, {"seg_id": 28, "text": "This is always true."}, {"seg_id": 29, "text": "*   However, the signature $(s_+, s_-)$ of the lattice and the properties of the discriminant form are related."}, {"seg_id": 30, "text": "*   For an even lattice, the signature $(n, 0)$ (since it's positive definite) must satisfy:"}, {"seg_id": 31, "text": "$s_+ - s_- \\equiv \\text{signature of the discriminant form} \\pmod{8}$."}, {"seg_id": 32, "text": "Wait, the standard result (Milnor/Husemoller or Conway/Sloane) is:"}, {"seg_id": 33, "text": "The signature $(s_+, s_-)$ of an even lattice $L$ and its discriminant form $q$ are related by:"}, {"seg_id": 34, "text": "$s_+ - s_- \\equiv \\text{sign}(q) \\pmod{8}$, where $\\text{sign}(q)$ is related to the Milgram formula."}, {"seg_id": 35, "text": "Actually, the condition is $s_+ - s_- \\equiv \\text{signature of } q \\pmod{8}$."}, {"seg_id": 36, "text": "*   Let $A_L = \\mathbb{Z}/2\\mathbb{Z}$."}, {"seg_id": 37, "text": "The only possible even discriminant form $q$ is defined by $q(1) = 1/2 \\pmod{1}$?"}, {"seg_id": 38, "text": "No, let's use the definition from Conway and Sloane (Sphere Packings, Lattices and Groups)."}, {"seg_id": 39, "text": "*   For an even lattice, the discriminant form $q$ is $q: A_L \\to \\mathbb{Q}/2\\mathbb{Z}$."}, {"seg_id": 40, "text": "*   For $A_L = \\mathbb{Z}/2\\mathbb{Z}$, the non-zero element $v$ has $q(v) \\in \\{1/2, 1, 3/2\\}$."}, {"seg_id": 41, "text": "*   Wait, for $L$ to be even, the diagonal of the Gram matrix is even."}, {"seg_id": 42, "text": "*   If $L$ is an even lattice, the signature $(p, q)$ must satisfy $p-q \\equiv \\text{signature of } (A_L, q) \\pmod{8}$."}, {"seg_id": 43, "text": "*   Let's look at the genus of $L$."}, {"seg_id": 44, "text": "The genus is determined by the signature and the discriminant form."}, {"seg_id": 45, "text": "*   For $n=17$ and $d=2$, we need the signature to be $(17, 0)$."}, {"seg_id": 46, "text": "*   The discriminant form $q$ on $A_L = \\mathbb{Z}/2\\mathbb{Z}$ is determined by $q(1) \\in \\mathbb{Q}/2\\mathbb{Z}$."}, {"seg_id": 47, "text": "*   Since $2 \\cdot 1 \\equiv 0 \\pmod{2\\mathbb{Z}}$ in the discriminant group, $q(2 \\cdot 1) = 4q(1) \\equiv 0 \\pmod{2\\mathbb{Z}}$ is not the right condition."}, {"seg_id": 48, "text": "The correct condition is $q(k \\cdot v) = k^2 q(v)$."}, {"seg_id": 49, "text": "So $q(0) = 0 \\pmod{2\\mathbb{Z}}$ and $q(v) = q(-v)$ is satisfied."}, {"seg_id": 50, "text": "*   Actually, for an even lattice $L$, $q(v)$ must satisfy $q(v) \\in \\mathbb{Q}/2\\mathbb{Z}$ such that $q(v) \\equiv \\dots$?"}, {"seg_id": 51, "text": "*   Let's use the classification of even lattices."}, {"seg_id": 52, "text": "*   Even lattices with $d=2$:"}, {"seg_id": 53, "text": "$L$ could be $E_8 \\oplus E_8 \\oplus \\dots$ something."}, {"seg_id": 54, "text": "If $n=8$, even unimodular is $E_8$."}, {"seg_id": 55, "text": "If $n=17$, we can't have $E_8 \\oplus E_8 \\oplus \\dots$."}, {"seg_id": 56, "text": "But we could have $E_8 \\oplus E_8 \\oplus A_1$."}, {"seg_id": 57, "text": "$E_8$ is even unimodular, $d(E_8) = 1$."}, {"seg_id": 58, "text": "$A_1$ is an even lattice (Gram matrix [2]), $d(A_1) = 2$."}, {"seg_id": 59, "text": "So $L = E_8 \\oplus E_8 \\oplus A_1$ is an even lattice of dimension $8+8+1 = 17$ and determinant $1 \\cdot 1 \\cdot 2 = 2$."}, {"seg_id": 60, "text": "*   Is there any other genus?"}, {"seg_id": 61, "text": "*   The discriminant group $A_L = \\mathbb{Z}/2\\mathbb{Z}$."}, {"seg_id": 62, "text": "The possible discriminant forms $q: \\mathbb{Z}/2\\mathbb{Z} \\to \\mathbb{Q}/2\\mathbb{Z}$ are $q(1) = 1/2 \\pmod{1}$ or $q(1) = 1 \\pmod{1}$?"}, {"seg_id": 63, "text": "No, $q$ must be a quadratic form."}, {"seg_id": 64, "text": "*   In $\\mathbb{Q}/2\\mathbb{Z}$, $q(1)$ can be $1/2$ or $1$."}, {"seg_id": 65, "text": "*   If $q(1) = 1/2$, then the signature $s_+ - s_- = 17 - 0 = 17 \\equiv 1 \\pmod{8}$."}, {"seg_id": 66, "text": "Is $q(1) = 1/2$ consistent with $1 \\equiv 1 \\pmod{8}$?"}, {"seg_id": 67, "text": "The signature of the discriminant form $q$ is defined by the Gauss sum:"}, {"seg_id": 68, "text": "$\\sum_{x \\in A_L} e^{i \\pi q(x)} = \\sqrt{|A_L|} e^{i \\pi \\text{sign}(q) / 4}$."}, {"seg_id": 69, "text": "Wait, the formula is $\\sum_{x \\in A_L} e^{i \\pi q(x)} = \\sqrt{|A_L|} e^{i \\pi \\text{sign}(q) / 4}$."}, {"seg_id": 70, "text": "Let's check $q(1) = 1/2$:"}, {"seg_id": 71, "text": "$\\sum_{x \\in \\{0, 1\\}} e^{i \\pi q(x)} = e^{i \\pi (0)} + e^{i \\pi (1/2)} = 1 + i = \\sqrt{2} e^{i \\pi / 4}$."}, {"seg_id": 72, "text": "So $\\text{sign}(q) = 1$."}, {"seg_id": 73, "text": "The signature $s_+ - s_- \\equiv \\text{sign}(q) \\pmod{8}$ gives $17 \\equiv 1 \\pmod{8}$, which is $1 \\equiv 1 \\pmod{8}$."}, {"seg_id": 74, "text": "This is correct."}, {"seg_id": 75, "text": "*   If $q(1) = 1$, then:"}, {"seg_id": 76, "text": "$\\sum_{x \\in \\{0, 1\\}} e^{i \\pi q(x)} = e^{i \\pi (0)} + e^{i \\pi (1)} = 1 - 1 = 0$."}, {"seg_id": 77, "text": "This doesn't match $\\sqrt{2} e^{i \\pi \\text{sign}(q) / 4}$, so $q(1)=1$ is not a possible discriminant form for an even lattice."}, {"seg_id": 78, "text": "*   Therefore, the only possible genus for an even lattice of dimension 17 and determinant 2 is the one with $A_L = \\mathbb{Z}/2\\mathbb{Z}$ and $q(1) = 1/2 \\pmod{2\\mathbb{Z}}$ (or $1/2 \\pmod{1}$?)."}, {"seg_id": 79, "text": "Wait, the definition of the discriminant form for an even lattice is $q: A_L \\to \\mathbb{Q}/2\\mathbb{Z}$."}, {"seg_id": 80, "text": "*   If $q(1) = 1/2$, the Gauss sum is $1+i$. $\\sqrt{2} e^{i \\pi / 4} \\implies \\text{sign}(q) = 1$."}, {"seg_id": 81, "text": "*   If $q(1) = 3/2$, the Gauss sum is $1-i$. $\\sqrt{2} e^{i \\pi (-1/4)} \\implies \\text{sign}(q) = -1 \\equiv 7 \\pmod{8}$."}, {"seg_id": 82, "text": "If $\\text{sign}(q) = 7$, then $17 \\equiv 7 \\pmod{8}$ is $1 \\equiv 7 \\pmod{8}$, which is false."}, {"seg_id": 83, "text": "*   So the genus is uniquely determined by $n=17$ and $d=2$."}, {"seg_id": 84, "text": "*   Now the question is: how many lattices are in this genus?"}, {"seg_id": 85, "text": "*   For large $n$, the number of lattices in a genus is typically 1."}, {"seg_id": 86, "text": "*   According to the theory of even lattices, for $n \\ge 2$ (actually higher), the number of even lattices in a genus is often 1, especially if the genus is not \"small\"."}, {"seg_id": 87, "text": "*   Wait, the question is \"How many positive definite even lattices are there of dimension 17 and determinant 2?\"."}, {"seg_id": 88, "text": "*   $E_8 \\oplus E_8 \\oplus A_1$ is one such lattice."}, {"seg_id": 89, "text": "*   The dimension is 17."}, {"seg_id": 90, "text": "*   The determinant is $1 \\cdot 1 \\cdot 2 = 2$."}, {"seg_id": 91, "text": "*   Is it the only one?"}, {"seg_id": 92, "text": "*   The number of lattices in a genus is given by the class number of the genus."}, {"seg_id": 93, "text": "*   For even unimodular lattices ($d=1$), the number of lattices in a genus:"}, {"seg_id": 94, "text": "- $n=8: 1$ ($E_8$)"}, {"seg_id": 95, "text": "- $n=16: 2$ ($E_8 \\oplus E_8$ and $D_{16}^+$)"}, {"seg_id": 96, "text": "- $n=24: 24$ (Niemeier lattices)"}, {"seg_id": 97, "text": "*   For $d=2$, let's see if there's any known result."}, {"seg_id": 98, "text": "*   The genus is determined by $(n, d, q)$."}, {"seg_id": 99, "text": "Here $n=17, d=2$, and $q(1)=1/2 \\pmod{1}$ (or $1/2 \\pmod{2}$?"}, {"seg_id": 100, "text": "No, $q: A_L \\to \\mathbb{Q}/2\\mathbb{Z}$ means $q(1)$ can be $1/2$ or $3/2$ or $1$ or $5/2...$ but it's in $\\mathbb{Q}/2\\mathbb{Z}$, so we only care about $1/2, 1, 3/2$)."}, {"seg_id": 101, "text": "*   Looking at the dimension $n=17$."}, {"seg_id": 102, "text": "For even unimodular lattices, the number of lattices in the genus increases with $n$ (at $n=16$, it's 2; at $n=24$, it's 24)."}, {"seg_id": 103, "text": "*   However, for $n=17$, what about $d=2$?"}, {"seg_id": 104, "text": "*   Wait, the number of even unimodular lattices of dimension $n$ is only non-zero if $8|n$."}, {"seg_id": 105, "text": "*   Our dimension is 17."}, {"seg_id": 106, "text": "*   Let's check the classification of even lattices of small dimension."}, {"seg_id": 107, "text": "*   For $n=1$, the only even lattice is $A_1$ (if we allow $d=2$)."}, {"seg_id": 108, "text": "*   For $n=9$, $E_8 \\oplus A_1$ has $d=2$."}, {"seg_id": 109, "text": "*   For $n=17$, $E_8 \\oplus E_8 \\oplus A_1$ has $d=2$."}, {"seg_id": 110, "text": "*   Could there be another lattice in the same genus?"}, {"seg_id": 111, "text": "*   The class number $h$ of a genus."}, {"seg_id": 112, "text": "For $n=17$, is it 1?"}, {"seg_id": 113, "text": "*   Let's check the case $n=16$ and $d=1$."}, {"seg_id": 114, "text": "The class number is 2."}, {"seg_id": 115, "text": "*   Wait, the question is $n=17, d=2$."}, {"seg_id": 116, "text": "This is slightly different from $n=16, d=1$."}, {"seg_id": 117, "text": "*   Actually, $E_8 \\oplus E_8 \\oplus A_1$ is a lattice of dimension 17 and $d=2$."}, {"seg_id": 118, "text": "*   Is there another even lattice of dimension 17 and $d=2$ that is not isomorphic to $E_8 \\oplus E_8 \\oplus A_1$?"}, {"seg_id": 119, "text": "*   Let $L$ be an even lattice of dimension 17 and $d=2$."}, {"seg_id": 120, "text": "*   Then $L$ could be $L' \\oplus A_1$ where $L'$ is an even unimodular lattice of dimension 16."}, {"seg_id": 121, "text": "*   There are two even unimodular lattices of dimension 16: $E_8 \\oplus E_8$ and $D_{16}^+$."}, {"seg_id": 122, "text": "*   So $L_1 = E_8 \\oplus E_8 \\oplus A_1$ and $L_2 = D_{16}^+ \\oplus A_1$."}, {"seg_id": 123, "text": "*   Wait, are $L_1$ and $L_2$ in the same genus?"}, {"seg_id": 124, "text": "*   Let's check their discriminant forms."}, {"seg_id": 125, "text": "*   The discriminant form of $A_1$ is $q_{A_1}(1) = 1/2 \\pmod{2\\mathbb{Z}}$ (using the $Q(x) = \\frac{1}{2}x^T A x$ convention, $A = [2]$, so $x^2 = 2 \\cdot (1/2)^2 = 1/2$."}, {"seg_id": 126, "text": "Wait, no."}, {"seg_id": 127, "text": "For $A_1$, the Gram matrix is $[2]$, the basis is $e$, $e^2=2$."}, {"seg_id": 128, "text": "The dual basis is $e^* = e/2$, so $(e^*)^2 = (e/2)^2 = 2/4 = 1/2$."}, {"seg_id": 129, "text": "So $q(e^*/e) = 1/2 \\pmod{2\\mathbb{Z}}$."}, {"seg_id": 130, "text": "Wait, is it $1/2 \\pmod{2\\mathbb{Z}}$ or $1/2 \\pmod{1}$?"}, {"seg_id": 131, "text": "In the definition of even lattices, $q(x) = x^2 \\pmod{2\\mathbb{Z}}$)."}, {"seg_id": 132, "text": "*   So $q_{A_1}(1) = 1/2 \\pmod{2\\mathbb{Z}}$."}, {"seg_id": 133, "text": "*   Now, for $L_1 = E_8 \\oplus E_8 \\oplus A_1$, the discriminant form is $q_{L_1} = q_{E_8} \\oplus q_{E_8} \\oplus q_{A_1} = 0 \\oplus 0 \\oplus q_{A_1}$."}, {"seg_id": 134, "text": "*   For $L_2 = D_{16}^+ \\oplus A_1$, the discriminant form is $q_{L_2} = q_{D_{16}^+} \\oplus q_{A_1} = 0 \\oplus q_{A_1}$."}, {"seg_id": 135, "text": "*   The discriminant forms are the same!"}, {"seg_id": 136, "text": "*   Wait, this means $L_1$ and $L_2$ are in the same genus."}, {"seg_id": 137, "text": "*   If $L_1$ and $L_2$ are in the same genus, then the class number is at least 2."}, {"seg_id": 138, "text": "*   Wait, but let me re-check $L_2$."}, {"seg_id": 139, "text": "Is $D_{16}^+$ an even unimodular lattice?"}, {"seg_id": 140, "text": "*   Yes, $D_{16}^+$ is one of the two even unimodular lattices of dimension 16."}, {"seg_id": 141, "text": "*   So $L_1 = E_8 \\oplus E_8 \\oplus A_1$ and $L_2 = D_{16}^+ \\oplus A_1$ are both even, dimension 17, determinant 2, and have the same discriminant form."}, {"seg_id": 142, "text": "*   Thus they belong to the same genus."}, {"seg_id": 143, "text": "*   The question is: are they isomorphic?"}, {"seg_id": 144, "text": "*   $E_8 \\oplus E_8$ is not isomorphic to $D_{16}^+$."}, {"seg_id": 145, "text": "*   Does $E_8 \\oplus E_8 \\oplus A_1 \\cong D_{16}^+ \\oplus A_1$?"}, {"seg_id": 146, "text": "*   This is equivalent to asking if the number of even unimodular lattices of dimension 16 is 2."}, {"seg_id": 147, "text": "*   If $L_1 \\cong L_2$, then $E_8 \\oplus E_8 \\oplus A_1 \\cong D_{16}^+ \\oplus A_1$."}, {"seg_id": 148, "text": "*   This would imply that the $A_1$ part is the same, but we can't easily conclude $E_8 \\oplus E_8 \\cong D_{16}^+$."}, {"seg_id": 149, "text": "*   Actually, if $M \\oplus A_1 \\cong N \\oplus A_1$, does it mean $M \\cong N$?"}, {"seg_id": 150, "text": "*   In general, for lattices, this is not always true, but for these specific unimodular lattices, $E_8 \\oplus E_8$ and $D_{16}^+$ are not isomorphic."}, {"seg_id": 151, "text": "*   The question is, if we add $A_1$, do they become isomorphic?"}, {"seg_id": 152, "text": "*   Let's check the properties of $E_8 \\oplus E_8$ and $D_{16}^+$."}, {"seg_id": 153, "text": "*   $E_8 \\oplus E_8$ is the direct sum of two $E_8$ lattices."}, {"seg_id": 154, "text": "*   $D_{16}^+$ is a different lattice."}, {"seg_id": 155, "text": "*   Wait, there's a theorem (by Witt or someone) about the cancellation property for lattices."}, {"seg_id": 156, "text": "*   For positive definite lattices, the cancellation property $M \\oplus L \\cong N \\oplus L \\implies M \\cong N$ does *not* always hold."}, {"seg_id": 157, "text": "*   However, for *unimodular* lattices, let's see."}, {"seg_id": 158, "text": "*   Actually, I can just look up the class number for this genus."}, {"seg_id": 159, "text": "*   The genus is $(n, d, q) = (17, 2, q_{A_1})$."}, {"seg_id": 160, "text": "*   The class number of the genus of $E_8 \\oplus E_8 \\oplus A_1$."}, {"seg_id": 161, "text": "*   Wait, the number of even unimodular lattices of dimension 16 is 2."}, {"seg_id": 162, "text": "*   The number of even unimodular lattices of dimension 24 is 24."}, {"seg_id": 163, "text": "*   The number of even unimodular lattices of dimension 8 is 1."}, {"seg_id": 164, "text": "*   The question is specifically about dimension 17 and determinant 2."}, {"seg_id": 165, "text": "*   Wait, I should check if $E_8 \\oplus E_8 \\oplus A_1$ and $D_{16}^+ \\oplus A_1$ are the only ones."}, {"seg_id": 166, "text": "*   Is it possible there are more?"}, {"seg_id": 167, "text": "*   Let's look at the dimension $n=17$ and $d=2$ more carefully."}, {"seg_id": 168, "text": "*   The question could be simpler."}, {"seg_id": 169, "text": "Let me re-read. \"How many positive definite even lattices are there of dimension 17 and determinant 2?\""}, {"seg_id": 170, "text": "*   Is there a connection to the number of Niemeier lattices?"}, {"seg_id": 171, "text": "No, that's $n=24, d=1$."}, {"seg_id": 172, "text": "*   Is there a connection to the number of even unimodular lattices of dimension 16?"}, {"seg_id": 173, "text": "*   Let's use the formula for the number of even lattices."}, {"seg_id": 174, "text": "*   Wait, I found a similar problem."}, {"seg_id": 175, "text": "For $n=16, d=1$, the answer is 2."}, {"seg_id": 176, "text": "*   Wait, I should check if $L_1$ and $L_2$ are the only ones in the genus."}, {"seg_id": 177, "text": "*   The genus of $E_8 \\oplus E_8 \\oplus A_1$ is the same as the genus of $D_{16}^+ \\oplus A_1$."}, {"seg_id": 178, "text": "*   The class number for even unimodular lattices of dimension 16 is 2."}, {"seg_id": 179, "text": "*   Does adding $A_1$ change the class number?"}, {"seg_id": 180, "text": "*   Let $h(G)$ be the class number of genus $G$."}, {"seg_id": 181, "text": "*   If $G$ is a genus of unimodular lattices, $h(G)$ is the number of even unimodular lattices of that dimension."}, {"seg_id": 182, "text": "*   For $G = (17, 2, q_{A_1})$, the class number $h(G)$ could be related to $h(16, 1, 0)$."}, {"seg_id": 183, "text": "*   In fact, there's a theorem that for $n \\ge 1$, $h(n, d, q)$ might be related to $h(n-1, d', q')$."}, {"seg_id": 184, "text": "*   Wait, the question might be from a context where the answer is a known value."}, {"seg_id": 185, "text": "*   Let me double check $n=17$ and $d=2$."}, {"seg_id": 186, "text": "*   $E_8 \\oplus E_8 \\oplus A_1$ (dim 17, det 2)"}, {"seg_id": 187, "text": "*   $D_{16}^+ \\oplus A_1$ (dim 17, det 2)"}, {"seg_id": 188, "text": "*   Wait, are there any others?"}, {"seg_id": 189, "text": "*   Let's check the genus of $A_{17}$?"}, {"seg_id": 190, "text": "No, $A_{17}$ has determinant 18."}, {"seg_id": 191, "text": "*   Let's check $E_8 \\oplus D_9$?"}, {"seg_id": 192, "text": "No, $D_9$ is not even unimodular."}, {"seg_id": 193, "text": "*   Wait, what if the answer is 1?"}, {"seg_id": 194, "text": "*   Let me re-calculate the number of even unimodular lattices of dimension 16."}, {"seg_id": 195, "text": "*   They are $E_8 \\oplus E_8$ and $D_{16}^+$."}, {"seg_id": 196, "text": "So there are 2."}, {"seg_id": 197, "text": "*   If $L_1 = E_8 \\oplus E_8 \\oplus A_1$ and $L_2 = D_{16}^+ \\oplus A_1$ are not isomorphic, then the answer is at least 2."}, {"seg_id": 198, "text": "*   Are they isomorphic?"}, {"seg_id": 199, "text": "*   $E_8 \\oplus E_8$ has a minimum norm of 2."}, {"seg_id": 200, "text": "*   $D_{16}^+$ also has a minimum norm of 2."}, {"seg_id": 201, "text": "*   The number of vectors of norm 2 in $E_8 \\oplus E_8$ is $240 + 240 = 480$."}, {"seg_id": 202, "text": "*   The number of vectors of norm 2 in $D_{16}^+$ is $2 \\times 16(16-1) = 2 \\times 16 \\times 15 = 480$."}, {"seg_id": 203, "text": "*   Wait, they have the same number of vectors of norm 2."}, {"seg_id": 204, "text": "This doesn't help."}, {"seg_id": 205, "text": "*   What about the number of vectors of norm 4?"}, {"seg_id": 206, "text": "*   For $E_8$, the theta series is $\\theta_{E_8}(z) = E_4(z)$."}, {"seg_id": 207, "text": "*   For $E_8 \\oplus E_8$, $\\theta_{E_8 \\oplus E_8}(z) = (E_4(z))^2$."}, {"seg_id": 208, "text": "*   For $D_{16}^+$, the theta series is also a modular form of weight 8 for $SL_2(\\mathbb{Z})$."}, {"seg_id": 209, "text": "*   The space of modular forms of weight 8 for $SL_2(\\mathbb{Z})$ is 1-dimensional, spanned by $E_4^2$ (or $E_8$)."}, {"seg_id": 210, "text": "*   This means the theta series of $E_8 \\oplus E_8$ and $D_{16}^+$ are *the same*!"}, {"seg_id": 211, "text": "*   Since they have the same theta series, we cannot distinguish them by their number of vectors of any norm."}, {"seg_id": 212, "text": "*   However, they are known to be non-isomorphic."}, {"seg_id": 213, "text": "*   So $L_1 = E_8 \\oplus E_8 \\oplus A_1$ and $L_2 = D_{16}^+ \\oplus A_1$ are two non-isomorphic lattices."}, {"seg_id": 214, "text": "*   Are they in the same genus?"}, {"seg_id": 215, "text": "Yes, we checked their discriminant forms."}, {"seg_id": 216, "text": "*   Is the class number of the genus of $E_8 \\oplus E_8 \\oplus A_1$ exactly 2?"}, {"seg_id": 217, "text": "*   Let's check the properties of the genus again."}, {"seg_id": 218, "text": "*   For a genus with $d=2$, $n=17$."}, {"seg_id": 219, "text": "*   The class number of a genus $(n, d, q)$ is often related to the class number of the unimodular genus."}, {"seg_id": 220, "text": "*   Actually, for $n=17, d=2$, the number of even lattices is indeed 2."}, {"seg_id": 221, "text": "*   Wait, I've seen this somewhere."}, {"seg_id": 222, "text": "Let me search for \"even lattices of dimension 17 and determinant 2\"."}, {"seg_id": 223, "text": "*   Looking at some sources..."}, {"seg_id": 224, "text": "*   There's a table of class numbers for even lattices."}, {"seg_id": 225, "text": "*   For $d=2$, the dimension $n$ could be anything."}, {"seg_id": 226, "text": "*   If $n=1$, $h=1$ ($A_1$)."}, {"seg_id": 227, "text": "*   If $n=9$, $h=1$ ($E_8 \\oplus A_1$)."}, {"seg_id": 228, "text": "*   Wait, if $n=9$, $h=1$."}, {"seg_id": 229, "text": "But for $n=16$, $h=2$."}, {"seg_id": 230, "text": "*   If $n=17$, $h=2$."}, {"seg_id": 231, "text": "*   Let me double-check the $n=9, d=2$ case."}, {"seg_id": 232, "text": "*   $n=9, d=2$, even lattices."}, {"seg_id": 233, "text": "The only even unimodular lattice of $n=8$ is $E_8$."}, {"seg_id": 234, "text": "*   The only even lattice of $n=1$ and $d=2$ is $A_1$."}, {"seg_id": 235, "text": "*   So $E_8 \\oplus A_1$ is a lattice of $n=9, d=2$."}, {"seg_id": 236, "text": "*   Is there any other?"}, {"seg_id": 237, "text": "*   A lattice of $n=9, d=2$ must have $A_L = \\mathbb{Z}/2\\mathbb{Z}$ and $q(1) = 1/2$."}, {"seg_id": 238, "text": "*   The signature $s_+ - s_- = 9 \\equiv 1 \\pmod{8}$."}, {"seg_id": 239, "text": "*   The Gauss sum for $q(1)=1/2$ is $1+i$, so $\\text{sign}(q)=1$."}, {"seg_id": 240, "text": "*   $9 \\equiv 1 \\pmod{8}$ is true."}, {"seg_id": 241, "text": "*   Is there any other even lattice of $n=9, d=2$?"}, {"seg_id": 242, "text": "*   For $n=9, d=2$, there is only one even unimodular lattice of dimension 8 ($E_8$) and one even lattice of dimension 1 ($A_1$)."}, {"seg_id": 243, "text": "*   The class number of $(9, 2, q_{A_1})$ is the same as the class number of $(8, 1, 0)$."}, {"seg_id": 244, "text": "*   Wait, the class number of $(8, 1, 0)$ is 1."}, {"seg_id": 245, "text": "*   The class number of $(16, 1, 0)$ is 2."}, {"seg_id": 246, "text": "*   So the class number of $(17, 2, q_{A_1})$ should be the same as the class number of $(16, 1, 0)$, which is 2."}, {"seg_id": 247, "text": "*   Is it possible that $E_8 \\oplus E_8 \\oplus A_1 \\cong D_{16}^+ \\oplus A_1$?"}, {"seg_id": 248, "text": "*   If they were isomorphic, the answer would be 1."}, {"seg_id": 249, "text": "*   But $E_8 \\oplus E_8$ and $D_{16}^+$ are not isomorphic."}, {"seg_id": 250, "text": "*   Does $M \\oplus A_1 \\cong N \\oplus A_1 \\implies M \\cong N$ for unimodular $M, N$?"}, {"seg_id": 251, "text": "*   For $M, N$ being even unimodular lattices, they are even more special."}, {"seg_id": 252, "text": "*   According to some literature, the cancellation property $M \\oplus L \\cong N \\oplus L \\implies M \\cong N$ holds for even unimodular lattices if the dimension is large."}, {"seg_id": 253, "text": "*   Actually, even for $n=16$, $E_8 \\oplus E_8 \\oplus A_1$ and $D_{16}^+ \\oplus A_1$ are not isomorphic."}, {"seg_id": 254, "text": "*   One way to see this is to look at the number of vectors of a certain norm."}, {"seg_id": 255, "text": "But we already saw that's not enough."}, {"seg_id": 256, "text": "*   Another way is to look at the automorphism group."}, {"seg_id": 257, "text": "*   $\\text{Aut}(E_8 \\oplus E_8 \\oplus A_1)$ is much larger than $\\text{Aut}(D_{16}^+ \\oplus A_1)$."}, {"seg_id": 258, "text": "*   $\\text{Aut}(E_8 \\oplus E_8 \\oplus A_1) = \\text{Aut}(E_8) \\wr S_2 \\times \\text{Aut}(A_1)$ (approximately)."}, {"seg_id": 259, "text": "*   $\\text{Aut}(D_{16}^+ \\oplus A_1) = \\text{Aut}(D_{16}^+) \\times \\text{Aut}(A_1)$."}, {"seg_id": 260, "text": "*   Wait, the question is just \"how many\"."}, {"seg_id": 261, "text": "*   Dimension $n=17$."}, {"seg_id": 262, "text": "*   Determinant $d=2$."}, {"seg_id": 263, "text": "*   Even lattice."}, {"seg_id": 264, "text": "*   Genus: $(17, 2, q_{A_1})$."}, {"seg_id": 265, "text": "*   Class number of this genus:"}, {"seg_id": 266, "text": "The genus of $(n, d, q)$ can be related to the genus of $(n-1, d, q')$ if $d$ is the same."}, {"seg_id": 267, "text": "If $L = L' \\oplus A_1$, then $L$ is an even lattice of dimension $n$ and determinant 2."}, {"seg_id": 268, "text": "$L'$ must be an even unimodular lattice of dimension $n-1$."}, {"seg_id": 269, "text": "For $n=17$, $n-1=16$."}, {"seg_id": 270, "text": "The number of even unimodular lattices of dimension 16 is 2."}, {"seg_id": 271, "text": "Thus, there are at least 2 even lattices of dimension 17 and determinant 2 ($E_8 \\oplus E_8 \\oplus A_1$ and $D_{16}^+ \\oplus A_1$)."}, {"seg_id": 272, "text": "*   Are there any other even lattices of dimension 17 and determinant 2 that are *not* of the form $L' \\oplus A_1$?"}, {"seg_id": 273, "text": "*   A lattice $L$ is in the genus $(17, 2, q_{A_1})$."}, {"seg_id": 274, "text": "*   If the class number of the genus $(16, 1, 0)$ is 2, then the class number of the genus $(17, 2, q_{A_1})$ is also 2."}, {"seg_id": 275, "text": "*   Wait, I should check if there are any other possible even lattices of $d=2$."}, {"seg_id": 276, "text": "*   The discriminant group must be $\\mathbb{Z}/2\\mathbb{Z}$ and the discriminant form must be $q(1) = 1/2 \\pmod{1}$."}, {"seg_id": 277, "text": "*   Is there any other possibility for $q$?"}, {"seg_id": 278, "text": "*   We already checked: $q(1) = 1 \\pmod{1}$ is impossible."}, {"seg_id": 279, "text": "*   $q(1) = 3/2 \\pmod{1}$ is the same as $q(1) = 1/2 \\pmod{1}$ in $\\mathbb{Q}/2\\mathbb{Z}$."}, {"seg_id": 280, "text": "*   Wait, $q(1)$ could be $1/2 \\pmod{2\\mathbb{Z}}$ or $3/2 \\pmod{2\\mathbb{Z}}$."}, {"seg_id": 281, "text": "*   But $q(1) = 3/2 \\pmod{2\\mathbb{Z}}$ gives $\\text{sign}(q) = -1 \\equiv 7 \\pmod{8}$."}, {"seg_id": 282, "text": "*   $n = 17 \\equiv 1 \\pmod{8}$."}, {"seg_id": 283, "text": "*   So we must have $\\text{sign}(q) = 1$, which means $q(1) = 1/2 \\pmod{2\\mathbb{Z}}$ is the only possibility."}, {"seg_id": 284, "text": "*   Thus, the genus is uniquely determined."}, {"seg_id": 285, "text": "*   And the class number of $(17, 2, q_{A_1})$ is the same as the class number of $(16, 1, 0)$, which is 2."}, {"seg_id": 286, "text": "*   The question asks for the number of positive definite even lattices of dimension 17 and determinant 2."}, {"seg_id": 287, "text": "*   Based on the genus and class number theory, the answer is 2."}, {"seg_id": 288, "text": "*   Let me double check:"}, {"seg_id": 289, "text": "$n=8, d=1 \\implies h=1$"}, {"seg_id": 290, "text": "$n=16, d=1 \\implies h=2$"}, {"seg_id": 291, "text": "$n=24, d=1 \\implies h=24$"}, {"seg_id": 292, "text": "$n=1, d=2 \\implies h=1$ (This is $A_1$)"}, {"seg_id": 293, "text": "$n=9, d=2 \\implies h=1$ ($E_8 \\oplus A_1$)"}, {"seg_id": 294, "text": "$n=17, d=2 \\implies h=2$ ($E_8 \\oplus E_8 \\oplus A_1$ and $D_{16}^+ \\oplus A_1$)"}, {"seg_id": 295, "text": "*   Could there be another lattice in the genus $(17, 2, q_{A_1})$ that's not $L' \\oplus A_1$?"}, {"seg_id": 296, "text": "*   For example, a lattice that's not a direct sum?"}, {"seg_id": 297, "text": "*   In the theory of lattices, the class number $h(n, d, q)$ is the number of isometry classes in the genus."}, {"seg_id": 298, "text": "*   For $n=17, d=2$, the genus is $G$."}, {"seg_id": 299, "text": "*   Is there any other lattice in $G$ besides $E_8 \\oplus E_8 \\oplus A_1$ and $D_{16}^+ \\oplus A_1$?"}, {"seg_id": 300, "text": "*   According to the theory of Niemeier lattices and their generalizations, for these dimensions, all lattices in the genus of $L \\oplus A_1$ are of the form $L' \\oplus A_1$."}, {"seg_id": 301, "text": "*   Wait, let me check this again."}, {"seg_id": 302, "text": "For $n=16$, the class number was 2."}, {"seg_id": 303, "text": "For $n=17$, the class number should also be 2."}, {"seg_id": 304, "text": "*   Let's check if $L$ being $L' \\oplus A_1$ is the only way."}, {"seg_id": 305, "text": "*   If $L$ is in the genus of $E_8 \\oplus E_8 \\oplus A_1$, then $L$ has $A_L = \\mathbb{Z}/2\\mathbb{Z}$."}, {"seg_id": 306, "text": "*   Let $v \\in L^*$ be the non-zero element. $2v \\in L$."}, {"seg_id": 307, "text": "*   Then $2v$ is a vector in $L$."}, {"seg_id": 308, "text": "*   If $v^2 = 1/2$, then $(2v)^2 = 4(1/2) = 2$."}, {"seg_id": 309, "text": "*   Let $x = 2v$."}, {"seg_id": 310, "text": "Then $x \\in L$ and $x^2 = 2$."}, {"seg_id": 311, "text": "*   Consider the sublattice $L' = \\{ y \\in L \\mid y \\cdot x = 0 \\}$."}, {"seg_id": 312, "text": "*   $L'$ has dimension 16 and is an even lattice."}, {"seg_id": 313, "text": "*   The determinant of $L'$ can be calculated."}, {"seg_id": 314, "text": "*   Since $L$ is even and $d(L)=2$, and $x^2=2$, the determinant of $L'$ is 1."}, {"seg_id": 315, "text": "*   Wait, $d(L) = d(L') \\cdot d(\\mathbb{Z}x) / (\\text{something related to } x \\cdot L^*)$."}, {"seg_id": 316, "text": "*   Actually, $d(L) = d(L') \\cdot (x^2) / (\\dots)$."}, {"seg_id": 317, "text": "*   More simply, $L'$ is a sublattice of $L$ of index 2 if we consider $L \\subset L'$."}, {"seg_id": 318, "text": "No."}, {"seg_id": 319, "text": "*   Let's use the fact that $x \\in L$ with $x^2=2$."}, {"seg_id": 320, "text": "*   Then $L$ is an extension of $L'$ by the vector $x$."}, {"seg_id": 321, "text": "*   Since $x^2=2$, $x$ can be seen as the $A_1$ part."}, {"seg_id": 322, "text": "*   So $L \\cong L' \\oplus A_1$ where $L'$ is an even unimodular lattice of dimension 16."}, {"seg_id": 323, "text": "*   Since there are exactly 2 such lattices $L'$, there are exactly 2 such $L$."}, {"seg_id": 324, "text": "*   Is it possible that $x$ is not \"separated\" from $L'$?"}, {"seg_id": 325, "text": "*   If $x^2=2$, then $L$ is always $L' \\oplus A_1$."}, {"seg_id": 326, "text": "*   Let's re-verify this."}, {"seg_id": 327, "text": "Let $x \\in L$ with $x^2=2$."}, {"seg_id": 328, "text": "Let $L' = \\{ y \\in L \\mid y \\cdot x = 0 \\}$."}, {"seg_id": 329, "text": "*   Then $L'$ is a lattice of dimension 16."}, {"seg_id": 330, "text": "*   Since $x \\in L$, $L = L' \\oplus \\mathbb{Z}x$ if and only if $x$ is orthogonal to $L'$."}, {"seg_id": 331, "text": "*   Is $x$ orthogonal to $L'$?"}, {"seg_id": 332, "text": "Yes, by definition of $L'$."}, {"seg_id": 333, "text": "*   Is $L$ the direct sum of $L'$ and $\\mathbb{Z}x$?"}, {"seg_id": 334, "text": "*   Any $y \\in L$ can be written as $y = y' + c x$ where $y' \\in L' \\otimes \\mathbb{Q}$ and $c \\in \\mathbb{Q}$."}, {"seg_id": 335, "text": "*   $y \\cdot x = y' \\cdot x + c x^2 = 0 + 2c$."}, {"seg_id": 336, "text": "*   Since $y \\in L$ and $x \\in L$, $y \\cdot x \\in \\mathbb{Z}$ (because $L$ is even and $x \\in L$, so $y \\cdot x$ is an integer?"}, {"seg_id": 337, "text": "Wait, $y \\cdot x$ is an integer for any even lattice)."}, {"seg_id": 338, "text": "*   So $2c = k \\in \\mathbb{Z}$, which means $c = k/2$."}, {"seg_id": 339, "text": "*   Also $y^2 = (y' + cx)^2 = y'^2 + c^2 x^2 = y'^2 + (k/2)^2 \\cdot 2 = y'^2 + k^2/2$."}, {"seg_id": 340, "text": "*   Since $y^2 \\in 2\\mathbb{Z}$ and $y'^2 \\in 2\\mathbb{Z}$ (if $L'$ is even), then $k^2/2$ must be an even integer?"}, {"seg_id": 341, "text": "No, $k^2/2$ must be an integer, so $k$ is even."}, {"seg_id": 342, "text": "*   Wait, if $k$ is even, then $c = k/2$ is an integer."}, {"seg_id": 343, "text": "*   If $c$ is an integer, then $y = y' + cx \\in L' \\oplus \\mathbb{Z}x$."}, {"seg_id": 344, "text": "*   So $L = L' \\oplus \\mathbb{Z}x$."}, {"seg_id": 345, "text": "*   Is $L'$ always even and unimodular?"}, {"seg_id": 346, "text": "*   $L'$ is even because it's a sublattice of an even lattice."}, {"seg_id": 347, "text": "*   $d(L) = d(L') \\cdot x^2 = d(L') \\cdot 2$."}, {"seg_id": 348, "text": "*   Since $d(L)=2$, $d(L')=1$."}, {"seg_id": 349, "text": "*   So $L'$ is an even unimodular lattice of dimension 16."}, {"seg_id": 350, "text": "*   Thus $L \\cong L' \\oplus A_1$."}, {"seg_id": 351, "text": "*   The number of such lattices is the number of such $L'$, which is 2."}, {"seg_id": 352, "text": "*   Wait, I assumed $x^2=2$ exists in $L$."}, {"seg_id": 353, "text": "*   Is it possible that there's no $x \\in L$ with $x^2=2$?"}, {"seg_id": 354, "text": "*   The determinant is 2, so the discriminant group is $\\mathbb{Z}/2\\mathbb{Z}$."}, {"seg_id": 355, "text": "*   The non-zero element $v \\in L^*/L$ has $q(v) = 1/2 \\pmod{2\\mathbb{Z}}$."}, {"seg_id": 356, "text": "*   This means $v^2 = 1/2 + 2k$ for some integer $k$."}, {"seg_id": 357, "text": "*   Since the lattice is positive definite, $v^2$ can be any value in $\\{1/2, 5/2, 9/2, \\dots\\}$."}, {"seg_id": 358, "text": "*   If $v^2 = 1/2$, we found $x = 2v$ has $x^2 = 4(1/2) = 2$."}, {"seg_id": 359, "text": "*   If $v^2 = 5/2$, then $x = 2v$ has $x^2 = 4(5/2) = 10$."}, {"seg_id": 360, "text": "*   But does every even lattice of dimension 17 and determinant 2 have a vector of norm 2?"}, {"seg_id": 361, "text": "*   Let's check $n=1, d=2$."}, {"seg_id": 362, "text": "The lattice is $A_1$, which has $x^2=2$."}, {"seg_id": 363, "text": "*   Let's check $n=9, d=2$."}, {"seg_id": 364, "text": "The lattice is $E_8 \\oplus A_1$, which has $x^2=2$."}, {"seg_id": 365, "text": "*   In fact, a theorem by Minkowski or someone says that for any lattice, there's a vector of small norm."}, {"seg_id": 366, "text": "*   But more specifically, for the genus of $E_8 \\oplus E_8 \\oplus A_1$, does every lattice in it have a vector of norm 2?"}, {"seg_id": 367, "text": "*   Wait, I just showed that if a lattice $L$ has a vector $x$ of norm 2, then $L \\cong L' \\oplus A_1$."}, {"seg_id": 368, "text": "*   Is it possible that the class number is higher because some lattices in the genus don't have a vector of norm 2?"}, {"seg_id": 369, "text": "*   Let's check the dimension $n=17$."}, {"seg_id": 370, "text": "For $n \\ge 1$, the number of vectors of norm 2 is given by the theta series."}, {"seg_id": 371, "text": "*   Wait, the theta series $\\theta_L(z)$ for all $L$ in the genus are *almost* the same."}, {"seg_id": 372, "text": "*   Actually, for $n=17$, the theta series $\\theta_L(z)$ are all the same because the space of modular forms of weight $17/2$ is not 1-dimensional, but the *genus* has a single theta series if $n$ is large?"}, {"seg_id": 373, "text": "No, that's not right."}, {"seg_id": 374, "text": "*   Wait, the theta series of all lattices in a genus are the same if the genus is \"large enough\"?"}, {"seg_id": 375, "text": "No, that's for the *average* theta series."}, {"seg_id": 376, "text": "*   However, for even unimodular lattices, the theta series are the same only if the dimension is $n=8, 16$."}, {"seg_id": 377, "text": "For $n=24$, they are not the same (that's why there are 24 Niemeier lattices, but they all have $d=1$ and the same $n$, yet their theta series are different)."}, {"seg_id": 378, "text": "*   Wait, if $n=24$ and $d=1$, there are 24 lattices and their theta series are different."}, {"seg_id": 379, "text": "*   But our dimension is 17, which is much smaller."}, {"seg_id": 380, "text": "*   Let's re-evaluate the $n=16, d=1$ case."}, {"seg_id": 381, "text": "The two lattices $E_8 \\oplus E_8$ and $D_{16}^+$ have the same theta series."}, {"seg_id": 382, "text": "*   Since they have the same theta series, they have the same number of vectors of norm 2."}, {"seg_id": 383, "text": "*   The number of vectors of norm 2 is 480 for both."}, {"seg_id": 384, "text": "*   So both lattices in the $n=16, d=1$ genus have a vector of norm 2."}, {"seg_id": 385, "text": "*   If we add $A_1$, both $E_8 \\oplus E_8 \\oplus A_1$ and $D_{16}^+ \\oplus A_1$ will have vectors of norm 2."}, {"seg_id": 386, "text": "*   Now, is it possible there's another lattice in the $(17, 2, q_{A_1})$ genus that *doesn't* have a vector of norm 2?"}, {"seg_id": 387, "text": "*   If it doesn't have a vector of norm 2, then its theta series $\\theta_L(z)$ must have $a_2 = 0$ (the coefficient of $q^2$)."}, {"seg_id": 388, "text": "*   But we just said that all lattices in the genus $(17, 2, q_{A_1})$ have the *same* theta series as $E_8 \\oplus E_8 \\oplus A_1$."}, {"seg_id": 389, "text": "*   Wait, is that true?"}, {"seg_id": 390, "text": "*   The theta series of any lattice in a genus $G$ are not necessarily the same."}, {"seg_id": 391, "text": "*   However, the *average* theta series is a modular form."}, {"seg_id": 392, "text": "*   But for $n=16, d=1$, the theta series of $E_8 \\oplus E_8$ and $D_{16}^+$ *are* the same."}, {"seg_id": 393, "text": "*   Therefore, the theta series of $E_8 \\oplus E_8 \\oplus A_1$ and $D_{16}^+ \\oplus A_1$ are also the same."}, {"seg_id": 394, "text": "*   Since $a_2 = 480$ for both, any lattice in the genus must have $a_2 = 480$."}, {"seg_id": 395, "text": "*   If $a_2 = 480$, then there is at least one vector of norm 2."}, {"seg_id": 396, "text": "*   And as I showed, if there's a vector of norm 2, the lattice must be of the form $L' \\oplus A_1$."}, {"seg_id": 397, "text": "*   So any lattice in the genus $(17, 2, q_{A_1})$ is of the form $L' \\oplus A_1$, where $L'$ is an even unimodular lattice of dimension 16."}, {"seg_id": 398, "text": "*   Since there are exactly 2 such $L'$, there are exactly 2 such lattices."}, {"seg_id": 399, "text": "*   Is it true that $\\theta_{E_8 \\oplus E_8} = \\theta_{D_{16}^+}$?"}, {"seg_id": 400, "text": "*   The space of modular forms of weight 8 for $SL_2(\\mathbb{Z})$ is 1-dimensional."}, {"seg_id": 401, "text": "*   The dimension is $k/12$ (approximately)."}, {"seg_id": 402, "text": "For $k=8$, the dimension is $\\lfloor 8/12 \\rfloor + 1$ if we consider $E_4, E_6$."}, {"seg_id": 403, "text": "Wait, $k=8$ is $E_4^2$."}, {"seg_id": 404, "text": "*   The basis is $\\{E_4^2\\}$."}, {"seg_id": 405, "text": "So the space is 1-dimensional."}, {"seg_id": 406, "text": "*   Since both $\\theta_{E_8 \\oplus E_8}$ and $\\theta_{D_{16}^+}$ are modular forms of weight 8, they must be multiples of each other."}, {"seg_id": 407, "text": "*   Since their first coefficient is 1, they must be equal."}, {"seg_id": 408, "text": "*   So yes, $\\theta_{E_8 \\oplus E_8} = \\theta_{D_{16}^+}$."}, {"seg_id": 409, "text": "*   This confirms the logic."}, {"seg_id": 410, "text": "*   Even lattices, $n=17, d=2$."}, {"seg_id": 411, "text": "*   $L_1 = E_8 \\oplus E_8 \\oplus A_1$."}, {"seg_id": 412, "text": "*   $L_2 = D_{16}^+ \\oplus A_1$."}, {"seg_id": 413, "text": "*   Both are in the same genus."}, {"seg_id": 414, "text": "*   They are not isomorphic because $E_8 \\oplus E_8 \\not\\cong D_{16}^+$."}, {"seg_id": 415, "text": "*   Any lattice in this genus must have a vector of norm 2."}, {"seg_id": 416, "text": "*   Any lattice with a vector of norm 2 and $d=2$ is of the form $L' \\oplus A_1$ with $L'$ even unimodular."}, {"seg_id": 417, "text": "*   There are only 2 such $L'$."}, {"seg_id": 418, "text": "*   So there are exactly 2 such lattices."}, {"seg_id": 419, "text": "*   Dimension 17?"}, {"seg_id": 420, "text": "Yes."}, {"seg_id": 421, "text": "*   Positive definite?"}, {"seg_id": 422, "text": "Yes."}, {"seg_id": 423, "text": "*   Even?"}, {"seg_id": 424, "text": "Yes."}, {"seg_id": 425, "text": "*   Determinant 2?"}, {"seg_id": 426, "text": "Yes."}, {"seg_id": 427, "text": "*   Number of them? 2."}, {"seg_id": 428, "text": "*   Wait, let me think about $n=16, d=1$."}, {"seg_id": 429, "text": "The number is 2."}, {"seg_id": 430, "text": "*   The dimension $n=17$ and $d=2$ seems to be the \"next\" case after $n=9, d=2$ (which has 1)."}, {"seg_id": 431, "text": "*   Wait, let's check $n=1, d=2$: $h=1$."}, {"seg_id": 432, "text": "*   $n=9, d=2$: $h=1$."}, {"seg_id": 433, "text": "*   $n=17, d=2$: $h=2$."}, {"seg_id": 434, "text": "*   $n=25, d=2$: $h=$ ?"}, {"seg_id": 435, "text": "(probably much larger)."}, {"seg_id": 436, "text": "*   This makes sense."}, {"seg_id": 437, "text": "The class number of the genus $(n, d, q)$ should be the same as the class number of the genus $(n-1, 1, 0)$ if $d=2$."}, {"seg_id": 438, "text": "*   Let me re-verify $n=9, d=2$."}, {"seg_id": 439, "text": "$n=9, d=2 \\implies n-1=8, d=1$."}, {"seg_id": 440, "text": "Number of even unimodular lattices of dim 8 is 1 ($E_8$)."}, {"seg_id": 441, "text": "So $h(9, 2, q_{A_1}) = h(8, 1, 0) = 1$."}, {"seg_id": 442, "text": "Correct."}, {"seg_id": 443, "text": "*   Let me re-verify $n=17, d=2$."}, {"seg_id": 444, "text": "$n=17, d=2 \\implies n-1=16, d=1$."}, {"seg_id": 445, "text": "Number of even unimodular lattices of dim 16 is 2 ($E_8 \\oplus E_8$ and $D_{16}^+$)."}, {"seg_id": 446, "text": "So $h(17, 2, q_{A_1}) = h(16, 1, 0) = 2$."}, {"seg_id": 447, "text": "Correct."}]}